{
    "entities": {
        "employee": {
            "14": {
                "age": "30", 
                "id": "14", 
                "name": "Ion", 
                "salary": "1000 EUR", 
                "type": "employee"
            }, 
            "15": {
                "id": "15", 
                "name": "Cosmin", 
                "salary": "2000 RON", 
                "type": "employee"
            }
        }, 
        "product": {
            "16": {
                "id": "16", 
                "name": "Salata", 
                "price": "16 RON", 
                "type": "product"
            }, 
            "17": {
                "id": "17", 
                "kcal": "500", 
                "name": "Gratar pui", 
                "price": "22 RON", 
                "type": "product"
            }
        }
    }, 
    "indexes": {
        "employee": 16, 
        "product": 18
    }
}